policy_notification/__init__.py
policy_notification/admin.py
policy_notification/apps.py
policy_notification/filters.py
policy_notification/gql_queries.py
policy_notification/models.py
policy_notification/notification_client.py
policy_notification/notification_dispatcher.py
policy_notification/schema.py
policy_notification/services.py
policy_notification/tasks.py
policy_notification/urls.py
policy_notification/utils.py
policy_notification/views.py
policy_notification/migrations/0001_initial.py
policy_notification/migrations/0002_indicationofpolicynotifications.py
policy_notification/migrations/0003_auto_20210620_1931.py
policy_notification/migrations/0004_add_default_notification_approval.py
policy_notification/migrations/0005_report_role_rights.py
policy_notification/migrations/0006_indicationofpolicynotifications_indication_details.py
policy_notification/migrations/0007_auto_20211017_1246.py
policy_notification/migrations/0008_existing_policies_indication.py
policy_notification/migrations/0009_indicationofpolicynotificationsdetails.py
policy_notification/migrations/0010_auto_20211019_1440.py
policy_notification/migrations/__init__.py
policy_notification/notification_eligibility_validators/__init__.py
policy_notification/notification_eligibility_validators/abstract_validator.py
policy_notification/notification_eligibility_validators/dataclasses.py
policy_notification/notification_eligibility_validators/not_eligible_notification_handler.py
policy_notification/notification_eligibility_validators/notification_eligibility_validation.py
policy_notification/notification_gateways/__init__.py
policy_notification/notification_gateways/abstract_sms_gateway.py
policy_notification/notification_gateways/eGASMSGateway.py
policy_notification/notification_gateways/exceptions.py
policy_notification/notification_gateways/text_notification_provider.py
policy_notification/notification_gateways/RequestBuilders/__init__.py
openimis_be_policy_notification-1.5.0.dist-info/LICENSE
openimis_be_policy_notification-1.5.0.dist-info/METADATA
openimis_be_policy_notification-1.5.0.dist-info/WHEEL
openimis_be_policy_notification-1.5.0.dist-info/top_level.txt
openimis_be_policy_notification-1.5.0.dist-info/RECORD
