Metadata-Version: 2.1
Name: openimis-be-policy-notification
Version: 1.5.0
Summary: The openIMIS Backend PolicyNotification reference module.
Home-page: https://openimis.org/
Author: Damian Borowiecki
Author-email: dborowiecki@soldevelo.com
License: GNU AGPL v3
Classifier: Environment :: Web Environment
Classifier: Framework :: Django
Classifier: Framework :: Django :: 2.1
Classifier: Intended Audience :: Developers
Classifier: License :: OSI Approved :: GNU Affero General Public License v3
Classifier: Operating System :: OS Independent
Classifier: Programming Language :: Python
Classifier: Programming Language :: Python :: 3.6
Classifier: Programming Language :: Python :: 3.7
License-File: LICENSE
Requires-Dist: django
Requires-Dist: django-db-signals
Requires-Dist: djangorestframework
